{
  "type": "FeatureCollection",
  "features": [
    {
      "type": "Feature",
      "geometry": {
        "type": "Polygon"
      },
      "properties": {
        "NAME_PY": "Xizang",
        "NAME_CH": "西藏",
        "NAME_FT": "西藏",
        "PRES_LOC": "",
        "LEV_RANK": "1",
        "NOTE_ID": 0,
        "OBJ_TYPE": "POLYGON",
        "SYS_ID": "25020",
        "GEO_SRC": "",
        "COMPILER": "",
        "GEOCOMP": "满志敏",
        "CHECKER": "邹逸麟",
        "ENT_DATE": "2001/06/30",
        "X_COORD": 86.82618,
        "Y_COORD": 31.41201,
        "AREA": 1438410
      }
    },
    {
      "type": "Feature",
      "geometry": {
        "type": "Polygon"
      },
      "properties": {
        "NAME_PY": "Nibuchu",
        "NAME_CH": "中俄尼布楚条约待议地",
        "NAME_FT": "中俄尼部署條約待議地",
        "PRES_LOC": "",
        "LEV_RANK": "1",
        "NOTE_ID": 0,
        "OBJ_TYPE": "POLYGON",
        "SYS_ID": "25021",
        "GEO_SRC": "",
        "COMPILER": "",
        "GEOCOMP": "满志敏",
        "CHECKER": "邹逸麟",
        "ENT_DATE": "2001/06/30",
        "X_COORD": 133.02625,
        "Y_COORD": 53.94088,
        "AREA": 28304
      }
    },
    {
      "type": "Feature",
      "geometry": {
        "type": "Polygon"
      },
      "properties": {
        "NAME_PY": "Xinjiang",
        "NAME_CH": "新疆",
        "NAME_FT": "新疆",
        "PRES_LOC": "",
        "LEV_RANK": "1",
        "NOTE_ID": 0,
        "OBJ_TYPE": "POLYGON",
        "SYS_ID": "25022",
        "GEO_SRC": "",
        "COMPILER": "",
        "GEOCOMP": "满志敏",
        "CHECKER": "邹逸麟",
        "ENT_DATE": "2001/06/30",
        "X_COORD": 83.07536,
        "Y_COORD": 42.1138,
        "AREA": 2510900
      }
    },
    {
      "type": "Feature",
      "geometry": {
        "type": "MultiPolygon"
      },
      "properties": {
        "NAME_PY": "Shengjing",
        "NAME_CH": "盛京",
        "NAME_FT": "盛京",
        "PRES_LOC": "",
        "LEV_RANK": "1",
        "NOTE_ID": 0,
        "OBJ_TYPE": "POLYGON",
        "SYS_ID": "25023",
        "GEO_SRC": "",
        "COMPILER": "",
        "GEOCOMP": "满志敏",
        "CHECKER": "邹逸麟",
        "ENT_DATE": "2001/06/30",
        "X_COORD": 122.65564,
        "Y_COORD": 40.84202,
        "AREA": 102799
      }
    },
    {
      "type": "Feature",
      "geometry": {
        "type": "Polygon"
      },
      "properties": {
        "NAME_PY": "Yunnan",
        "NAME_CH": "云南",
        "NAME_FT": "雲南",
        "PRES_LOC": "",
        "LEV_RANK": "1",
        "NOTE_ID": 0,
        "OBJ_TYPE": "POLYGON",
        "SYS_ID": "25024",
        "GEO_SRC": "",
        "COMPILER": "",
        "GEOCOMP": "满志敏",
        "CHECKER": "邹逸麟",
        "ENT_DATE": "2001/06/30",
        "X_COORD": 101.77803,
        "Y_COORD": 25.17224,
        "AREA": 417798
      }
    },
    {
      "type": "Feature",
      "geometry": {
        "type": "Polygon"
      },
      "properties": {
        "NAME_PY": "Heilongjiang",
        "NAME_CH": "黑龙江",
        "NAME_FT": "黑龍江",
        "PRES_LOC": "",
        "LEV_RANK": "1",
        "NOTE_ID": 0,
        "OBJ_TYPE": "POLYGON",
        "SYS_ID": "25025",
        "GEO_SRC": "",
        "COMPILER": "",
        "GEOCOMP": "满志敏",
        "CHECKER": "邹逸麟",
        "ENT_DATE": "2001/06/30",
        "X_COORD": 125.29645,
        "Y_COORD": 50.80618,
        "AREA": 924516
      }
    },
    {
      "type": "Feature",
      "geometry": {
        "type": "MultiPolygon"
      },
      "properties": {
        "NAME_PY": "Jinlin",
        "NAME_CH": "吉林",
        "NAME_FT": "吉林",
        "PRES_LOC": "",
        "LEV_RANK": "1",
        "NOTE_ID": 0,
        "OBJ_TYPE": "POLYGON",
        "SYS_ID": "25026",
        "GEO_SRC": "",
        "COMPILER": "",
        "GEOCOMP": "满志敏",
        "CHECKER": "邹逸麟",
        "ENT_DATE": "2001/06/30",
        "X_COORD": 134.44638,
        "Y_COORD": 47.98264,
        "AREA": 997904
      }
    },
    {
      "type": "Feature",
      "geometry": {
        "type": "Polygon"
      },
      "properties": {
        "NAME_PY": "Wuliyasutai",
        "NAME_CH": "乌里雅苏台",
        "NAME_FT": "烏里雅蘇台",
        "PRES_LOC": "",
        "LEV_RANK": "1",
        "NOTE_ID": 0,
        "OBJ_TYPE": "POLYGON",
        "SYS_ID": "25027",
        "GEO_SRC": "",
        "COMPILER": "",
        "GEOCOMP": "满志敏",
        "CHECKER": "邹逸麟",
        "ENT_DATE": "2001/06/30",
        "X_COORD": 101.28736,
        "Y_COORD": 47.60334,
        "AREA": 1983640
      }
    },
    {
      "type": "Feature",
      "geometry": {
        "type": "Polygon"
      },
      "properties": {
        "NAME_PY": "Qinghai",
        "NAME_CH": "青海",
        "NAME_FT": "青海",
        "PRES_LOC": "",
        "LEV_RANK": "1",
        "NOTE_ID": 0,
        "OBJ_TYPE": "POLYGON",
        "SYS_ID": "25028",
        "GEO_SRC": "",
        "COMPILER": "",
        "GEOCOMP": "满志敏",
        "CHECKER": "邹逸麟",
        "ENT_DATE": "2001/06/30",
        "X_COORD": 95.97999,
        "Y_COORD": 35.26864,
        "AREA": 645031
      }
    },
    {
      "type": "Feature",
      "geometry": {
        "type": "Polygon"
      },
      "properties": {
        "NAME_PY": "Shaanxi",
        "NAME_CH": "陕西",
        "NAME_FT": "陝西",
        "PRES_LOC": "",
        "LEV_RANK": "1",
        "NOTE_ID": 0,
        "OBJ_TYPE": "POLYGON",
        "SYS_ID": "25029",
        "GEO_SRC": "",
        "COMPILER": "",
        "GEOCOMP": "满志敏",
        "CHECKER": "邹逸麟",
        "ENT_DATE": "2002/10/31",
        "X_COORD": 109.58463,
        "Y_COORD": 35.54087,
        "AREA": 190767
      }
    },
    {
      "type": "Feature",
      "geometry": {
        "type": "Polygon"
      },
      "properties": {
        "NAME_PY": "Anhui",
        "NAME_CH": "安徽",
        "NAME_FT": "安徽",
        "PRES_LOC": "",
        "LEV_RANK": "1",
        "NOTE_ID": 0,
        "OBJ_TYPE": "POLYGON",
        "SYS_ID": "25030",
        "GEO_SRC": "",
        "COMPILER": "",
        "GEOCOMP": "满志敏",
        "CHECKER": "邹逸麟",
        "ENT_DATE": "2001/06/30",
        "X_COORD": 117.25979,
        "Y_COORD": 31.55435,
        "AREA": 144893
      }
    },
    {
      "type": "Feature",
      "geometry": {
        "type": "Polygon"
      },
      "properties": {
        "NAME_PY": "Hubei",
        "NAME_CH": "湖北",
        "NAME_FT": "湖北",
        "PRES_LOC": "",
        "LEV_RANK": "1",
        "NOTE_ID": 0,
        "OBJ_TYPE": "POLYGON",
        "SYS_ID": "25031",
        "GEO_SRC": "",
        "COMPILER": "",
        "GEOCOMP": "满志敏",
        "CHECKER": "邹逸麟",
        "ENT_DATE": "2002/10/31",
        "X_COORD": 112.26328,
        "Y_COORD": 31.15641,
        "AREA": 183761
      }
    },
    {
      "type": "Feature",
      "geometry": {
        "type": "Polygon"
      },
      "properties": {
        "NAME_PY": "Hunan",
        "NAME_CH": "湖南",
        "NAME_FT": "湖南",
        "PRES_LOC": "",
        "LEV_RANK": "1",
        "NOTE_ID": 0,
        "OBJ_TYPE": "POLYGON",
        "SYS_ID": "25032",
        "GEO_SRC": "",
        "COMPILER": "",
        "GEOCOMP": "满志敏",
        "CHECKER": "邹逸麟",
        "ENT_DATE": "2002/10/31",
        "X_COORD": 111.51873,
        "Y_COORD": 27.38116,
        "AREA": 212574
      }
    },
    {
      "type": "Feature",
      "geometry": {
        "type": "MultiPolygon"
      },
      "properties": {
        "NAME_PY": "Guangdong",
        "NAME_CH": "广东",
        "NAME_FT": "广东",
        "PRES_LOC": "",
        "LEV_RANK": "1",
        "NOTE_ID": 0,
        "OBJ_TYPE": "POLYGON",
        "SYS_ID": "25033",
        "GEO_SRC": "",
        "COMPILER": "",
        "GEOCOMP": "满志敏",
        "CHECKER": "邹逸麟",
        "ENT_DATE": "2002/10/31",
        "X_COORD": 112.33343,
        "Y_COORD": 21.8406,
        "AREA": 226057
      }
    },
    {
      "type": "Feature",
      "geometry": {
        "type": "MultiPolygon"
      },
      "properties": {
        "NAME_PY": "Fujian",
        "NAME_CH": "福建",
        "NAME_FT": "福建",
        "PRES_LOC": "",
        "LEV_RANK": "1",
        "NOTE_ID": 0,
        "OBJ_TYPE": "POLYGON",
        "SYS_ID": "25034",
        "GEO_SRC": "",
        "COMPILER": "",
        "GEOCOMP": "满志敏",
        "CHECKER": "邹逸麟",
        "ENT_DATE": "2002/10/31",
        "X_COORD": 118.14541,
        "Y_COORD": 25.94086,
        "AREA": 159806
      }
    },
    {
      "type": "Feature",
      "geometry": {
        "type": "MultiPolygon"
      },
      "properties": {
        "NAME_PY": "Zhejiang",
        "NAME_CH": "浙江",
        "NAME_FT": "浙江",
        "PRES_LOC": "",
        "LEV_RANK": "1",
        "NOTE_ID": 0,
        "OBJ_TYPE": "POLYGON",
        "SYS_ID": "25035",
        "GEO_SRC": "",
        "COMPILER": "",
        "GEOCOMP": "满志敏",
        "CHECKER": "邹逸麟",
        "ENT_DATE": "2002/10/31",
        "X_COORD": 120.23102,
        "Y_COORD": 29.19472,
        "AREA": 103867
      }
    },
    {
      "type": "Feature",
      "geometry": {
        "type": "Polygon"
      },
      "properties": {
        "NAME_PY": "Zhili",
        "NAME_CH": "直隶",
        "NAME_FT": "直隸",
        "PRES_LOC": "",
        "LEV_RANK": "1",
        "NOTE_ID": 0,
        "OBJ_TYPE": "POLYGON",
        "SYS_ID": "25036",
        "GEO_SRC": "",
        "COMPILER": "",
        "GEOCOMP": "满志敏",
        "CHECKER": "邹逸麟",
        "ENT_DATE": "2002/10/31",
        "X_COORD": 117.64316,
        "Y_COORD": 39.89394,
        "AREA": 355394
      }
    },
    {
      "type": "Feature",
      "geometry": {
        "type": "Polygon"
      },
      "properties": {
        "NAME_PY": "Henan",
        "NAME_CH": "河南",
        "NAME_FT": "河南",
        "PRES_LOC": "",
        "LEV_RANK": "1",
        "NOTE_ID": 0,
        "OBJ_TYPE": "POLYGON",
        "SYS_ID": "25037",
        "GEO_SRC": "",
        "COMPILER": "",
        "GEOCOMP": "满志敏",
        "CHECKER": "邹逸麟",
        "ENT_DATE": "2001/06/30",
        "X_COORD": 113.44322,
        "Y_COORD": 34.08063,
        "AREA": 167100
      }
    },
    {
      "type": "Feature",
      "geometry": {
        "type": "MultiPolygon"
      },
      "properties": {
        "NAME_PY": "Neimenggu",
        "NAME_CH": "内蒙古",
        "NAME_FT": "内蒙古",
        "PRES_LOC": "",
        "LEV_RANK": "1",
        "NOTE_ID": 0,
        "OBJ_TYPE": "POLYGON",
        "SYS_ID": "25038",
        "GEO_SRC": "",
        "COMPILER": "",
        "GEOCOMP": "满志敏",
        "CHECKER": "邹逸麟",
        "ENT_DATE": "2001/06/30",
        "X_COORD": 111.24356,
        "Y_COORD": 42.39682,
        "AREA": 949787
      }
    },
    {
      "type": "Feature",
      "geometry": {
        "type": "Polygon"
      },
      "properties": {
        "NAME_PY": "Shanxi",
        "NAME_CH": "山西",
        "NAME_FT": "山西",
        "PRES_LOC": "",
        "LEV_RANK": "1",
        "NOTE_ID": 0,
        "OBJ_TYPE": "POLYGON",
        "SYS_ID": "25039",
        "GEO_SRC": "",
        "COMPILER": "",
        "GEOCOMP": "满志敏",
        "CHECKER": "邹逸麟",
        "ENT_DATE": "2001/06/30",
        "X_COORD": 112.24277,
        "Y_COORD": 38.07427,
        "AREA": 183510
      }
    },
    {
      "type": "Feature",
      "geometry": {
        "type": "Polygon"
      },
      "properties": {
        "NAME_PY": "Gansu",
        "NAME_CH": "甘肃",
        "NAME_FT": "甘肅",
        "PRES_LOC": "",
        "LEV_RANK": "1",
        "NOTE_ID": 0,
        "OBJ_TYPE": "POLYGON",
        "SYS_ID": "25040",
        "GEO_SRC": "",
        "COMPILER": "",
        "GEOCOMP": "满志敏",
        "CHECKER": "邹逸麟",
        "ENT_DATE": "2001/06/30",
        "X_COORD": 102.33739,
        "Y_COORD": 37.65251,
        "AREA": 540583
      }
    },
    {
      "type": "Feature",
      "geometry": {
        "type": "MultiPolygon"
      },
      "properties": {
        "NAME_PY": "Sichuan",
        "NAME_CH": "四川",
        "NAME_FT": "四川",
        "PRES_LOC": "",
        "LEV_RANK": "1",
        "NOTE_ID": 0,
        "OBJ_TYPE": "POLYGON",
        "SYS_ID": "25041",
        "GEO_SRC": "",
        "COMPILER": "",
        "GEOCOMP": "满志敏",
        "CHECKER": "邹逸麟",
        "ENT_DATE": "2001/06/30",
        "X_COORD": 103.78422,
        "Y_COORD": 30.19001,
        "AREA": 621431
      }
    },
    {
      "type": "Feature",
      "geometry": {
        "type": "Polygon"
      },
      "properties": {
        "NAME_PY": "Guizhou",
        "NAME_CH": "贵州",
        "NAME_FT": "貴州",
        "PRES_LOC": "",
        "LEV_RANK": "1",
        "NOTE_ID": 0,
        "OBJ_TYPE": "POLYGON",
        "SYS_ID": "25042",
        "GEO_SRC": "",
        "COMPILER": "",
        "GEOCOMP": "满志敏",
        "CHECKER": "邹逸麟",
        "ENT_DATE": "2001/06/30",
        "X_COORD": 106.5526,
        "Y_COORD": 26.92137,
        "AREA": 176166
      }
    },
    {
      "type": "Feature",
      "geometry": {
        "type": "Polygon"
      },
      "properties": {
        "NAME_PY": "Jiangxi",
        "NAME_CH": "江西",
        "NAME_FT": "江西",
        "PRES_LOC": "",
        "LEV_RANK": "1",
        "NOTE_ID": 0,
        "OBJ_TYPE": "POLYGON",
        "SYS_ID": "25043",
        "GEO_SRC": "",
        "COMPILER": "",
        "GEOCOMP": "满志敏",
        "CHECKER": "邹逸麟",
        "ENT_DATE": "2001/06/30",
        "X_COORD": 116.02689,
        "Y_COORD": 27.28384,
        "AREA": 165263
      }
    },
    {
      "type": "Feature",
      "geometry": {
        "type": "Polygon"
      },
      "properties": {
        "NAME_PY": "Guangxi",
        "NAME_CH": "广西",
        "NAME_FT": "廣西",
        "PRES_LOC": "",
        "LEV_RANK": "1",
        "NOTE_ID": 0,
        "OBJ_TYPE": "POLYGON",
        "SYS_ID": "25044",
        "GEO_SRC": "",
        "COMPILER": "",
        "GEOCOMP": "满志敏",
        "CHECKER": "邹逸麟",
        "ENT_DATE": "2001/06/30",
        "X_COORD": 108.50459,
        "Y_COORD": 23.9907,
        "AREA": 222880
      }
    },
    {
      "type": "Feature",
      "geometry": {
        "type": "MultiPolygon"
      },
      "properties": {
        "NAME_PY": "Shandong",
        "NAME_CH": "山东",
        "NAME_FT": "山東",
        "PRES_LOC": "",
        "LEV_RANK": "1",
        "NOTE_ID": 0,
        "OBJ_TYPE": "POLYGON",
        "SYS_ID": "25045",
        "GEO_SRC": "",
        "COMPILER": "",
        "GEOCOMP": "满志敏",
        "CHECKER": "邹逸麟",
        "ENT_DATE": "2001/06/30",
        "X_COORD": 118.88338,
        "Y_COORD": 36.3613,
        "AREA": 152972
      }
    },
    {
      "type": "Feature",
      "geometry": {
        "type": "MultiPolygon"
      },
      "properties": {
        "NAME_PY": "Jiangsu",
        "NAME_CH": "江苏",
        "NAME_FT": "江蘇",
        "PRES_LOC": "",
        "LEV_RANK": "1",
        "NOTE_ID": 0,
        "OBJ_TYPE": "POLYGON",
        "SYS_ID": "25046",
        "GEO_SRC": "",
        "COMPILER": "",
        "GEOCOMP": "满志敏",
        "CHECKER": "邹逸麟",
        "ENT_DATE": "2002/10/31",
        "X_COORD": 119.49252,
        "Y_COORD": 32.88607,
        "AREA": 105441
      }
    },
    {
      "type": "Feature",
      "geometry": {
        "type": "MultiPolygon"
      },
      "properties": {
        "NAME_PY": "Wanlichangsha",
        "NAME_CH": "万里长沙",
        "NAME_FT": "萬里長沙",
        "PRES_LOC": "",
        "LEV_RANK": "1",
        "NOTE_ID": 0,
        "OBJ_TYPE": "POLYGON",
        "SYS_ID": "25047",
        "GEO_SRC": "",
        "COMPILER": "",
        "GEOCOMP": "满志敏",
        "CHECKER": "邹逸麟",
        "ENT_DATE": "2001/06/30",
        "X_COORD": 111.59792,
        "Y_COORD": 16.23403,
        "AREA": 412.376
      }
    },
    {
      "type": "Feature",
      "geometry": {
        "type": "MultiPolygon"
      },
      "properties": {
        "NAME_PY": "Qianlishitang",
        "NAME_CH": "千里石塘",
        "NAME_FT": "千里石塘",
        "PRES_LOC": "",
        "LEV_RANK": "1",
        "NOTE_ID": 0,
        "OBJ_TYPE": "POLYGON",
        "SYS_ID": "25048",
        "GEO_SRC": "",
        "COMPILER": "",
        "GEOCOMP": "满志敏",
        "CHECKER": "邹逸麟",
        "ENT_DATE": "2001/06/30",
        "X_COORD": 113.34569,
        "Y_COORD": 8.21353,
        "AREA": 820.808
      }
    },
    {
      "type": "Feature",
      "geometry": {
        "type": "MultiPolygon"
      },
      "properties": {
        "NAME_PY": "Zengmu'ansha",
        "NAME_CH": "曾母暗沙",
        "NAME_FT": "曾母暗沙",
        "PRES_LOC": "",
        "LEV_RANK": "1",
        "NOTE_ID": 0,
        "OBJ_TYPE": "POLYGON",
        "SYS_ID": "25049",
        "GEO_SRC": "",
        "COMPILER": "",
        "GEOCOMP": "满志敏",
        "CHECKER": "邹逸麟",
        "ENT_DATE": "2001/06/30",
        "X_COORD": 112.27887,
        "Y_COORD": 3.97088,
        "AREA": 11.6805
      }
    },
    {
      "type": "Feature",
      "geometry": {
        "type": "MultiPolygon"
      },
      "properties": {
        "NAME_PY": "Dongsha",
        "NAME_CH": "东沙",
        "NAME_FT": "東沙",
        "PRES_LOC": "",
        "LEV_RANK": "1",
        "NOTE_ID": 0,
        "OBJ_TYPE": "POLYGON",
        "SYS_ID": "25050",
        "GEO_SRC": "",
        "COMPILER": "",
        "GEOCOMP": "满志敏",
        "CHECKER": "邹逸麟",
        "ENT_DATE": "2001/06/30",
        "X_COORD": 116.90872,
        "Y_COORD": 20.67474,
        "AREA": 69.6332
      }
    },
    {
      "type": "Feature",
      "geometry": {
        "type": "Polygon"
      },
      "properties": {
        "NAME_PY": "Zhongsha",
        "NAME_CH": "中沙",
        "NAME_FT": "中沙",
        "PRES_LOC": "",
        "LEV_RANK": "1",
        "NOTE_ID": 0,
        "OBJ_TYPE": "POLYGON",
        "SYS_ID": "25051",
        "GEO_SRC": "",
        "COMPILER": "",
        "GEOCOMP": "满志敏",
        "CHECKER": "邹逸麟",
        "ENT_DATE": "2001/06/30",
        "X_COORD": 117.79446,
        "Y_COORD": 15.1731,
        "AREA": 48.3204
      }
    }
  ]
}